pyhowdoi/__init__.py
pyhowdoi/main.py
pyhowdoi-1.2.1.dist-info/LICENSE.txt
pyhowdoi-1.2.1.dist-info/METADATA
pyhowdoi-1.2.1.dist-info/WHEEL
pyhowdoi-1.2.1.dist-info/entry_points.txt
pyhowdoi-1.2.1.dist-info/RECORD
