Metadata-Version: 2.1
Name: pyhowdoi
Version: 1.2.1
Summary: Use ChatGPT for quick command-line advice
Home-page: https://github.com/Thomas-McKanna/pyhowdoi
License: MIT
Author: Thomas McKanna
Author-email: thomasmckanna@proton.me
Requires-Python: >=3.10,<4.0
Classifier: License :: OSI Approved :: MIT License
Classifier: Programming Language :: Python :: 3
Classifier: Programming Language :: Python :: 3.10
Classifier: Programming Language :: Python :: 3.11
Requires-Dist: dependency (>=0.0.3,<0.0.4)
Requires-Dist: simplechatgpt (>=1.2.0,<2.0.0)
